DRE-1.1.27.dist-info/top_level.txt
DRE-1.1.27.dist-info/LICENSE
DRE-1.1.27.dist-info/RECORD
DRE-1.1.27.dist-info/METADATA
DRE-1.1.27.dist-info/WHEEL
DRE/_utils_tsne.cpython-37m-x86_64-linux-gnu.so
DRE/__init__.py
DRE/_utils_dre.py
DRE/setup.py
DRE/_models.py
DRE/_dre.py
