Metadata-Version: 2.1
Name: DRE
Version: 1.1.27
Summary: Deep Recursive Embedding for High-Dimensional Data
Home-page: https://github.com/zuxinrui/DRE
Author: Xinrui Zu
Author-email: zuxinrui95@gmail.com
License: LICENSE
Keywords: Dimensionality Reduction t-SNE UMAP Representation Learning
Platform: UNKNOWN
Classifier: Intended Audience :: Science/Research
Classifier: Intended Audience :: Developers
Classifier: Programming Language :: C
Classifier: Programming Language :: Python
Classifier: Topic :: Software Development
Classifier: Topic :: Scientific/Engineering
Classifier: Operating System :: Microsoft :: Windows
Classifier: Operating System :: POSIX
Classifier: Operating System :: Unix
Classifier: Operating System :: MacOS
Classifier: Programming Language :: Python :: 3
Classifier: Programming Language :: Python :: 3.7
Classifier: Programming Language :: Python :: 3.8
Classifier: Programming Language :: Python :: 3.9
Classifier: Programming Language :: Python :: Implementation :: CPython
Classifier: License :: OSI Approved :: MIT License
License-File: LICENSE
Requires-Dist: scikit-learn (>=0.16)
Requires-Dist: numba (>=0.34)
Requires-Dist: torch (>=1.0)
Requires-Dist: tqdm
Requires-Dist: ipywidgets
